[
    {
        "name": "KPop Demon Hunters",
        "rank": 1
    },
    {
        "name": "Anaconda: Cursed Jungle",
        "rank": 2
    },
    {
        "name": "Mantis",
        "rank": 3
    },
    {
        "name": "Legends of the Condor Heroes: The Gallants",
        "rank": 4
    },
    {
        "name": "Monk Comes Down the Mountain",
        "rank": 5
    },
    {
        "name": "Until Dawn",
        "rank": 6
    },
    {
        "name": "Man on Fire",
        "rank": 7
    },
    {
        "name": "The Bravest",
        "rank": 8
    },
    {
        "name": "Initial D",
        "rank": 9
    },
    {
        "name": "She Said Maybe",
        "rank": 10
    }
]