[
    {
        "name": "Apex",
        "rank": 1
    },
    {
        "name": "Migration",
        "rank": 2
    },
    {
        "name": "Swapped",
        "rank": 3
    },
    {
        "name": "Trust",
        "rank": 4
    },
    {
        "name": "The Super Mario Bros. Movie",
        "rank": 5
    },
    {
        "name": "The Inevitable Defeat of Mister & Pete",
        "rank": 6
    },
    {
        "name": "Mechanic: Resurrection",
        "rank": 7
    },
    {
        "name": "Finders Keepers",
        "rank": 8
    },
    {
        "name": "Hercules",
        "rank": 9
    },
    {
        "name": "Bleeding Steel",
        "rank": 10
    }
]