[
    {
        "name": "Sisu",
        "rank": 1
    },
    {
        "name": "The Great Flood",
        "rank": 2
    },
    {
        "name": "Dr. Seuss' The Grinch",
        "rank": 3
    },
    {
        "name": "Godzilla x Kong: The New Empire",
        "rank": 4
    },
    {
        "name": "My Secret Santa",
        "rank": 5
    },
    {
        "name": "My Wife's Ex",
        "rank": 6
    },
    {
        "name": "Jingle Bell Heist",
        "rank": 7
    },
    {
        "name": "Wake Up Dead Man: A Knives Out Mystery",
        "rank": 8
    },
    {
        "name": "The Fall Guy",
        "rank": 9
    },
    {
        "name": "Dune: Part Two",
        "rank": 10
    }
]