[
    {
        "name": "The Thursday Murder Club",
        "rank": 1
    },
    {
        "name": "KPop Demon Hunters",
        "rank": 2
    },
    {
        "name": "Unknown Number: The High School Catfish",
        "rank": 3
    },
    {
        "name": "Fall for Me",
        "rank": 4
    },
    {
        "name": "The Watchers",
        "rank": 5
    },
    {
        "name": "My Oxford Year",
        "rank": 6
    },
    {
        "name": "Abandoned Man",
        "rank": 7
    },
    {
        "name": "The Longest Yard",
        "rank": 8
    },
    {
        "name": "2 Hearts",
        "rank": 9
    },
    {
        "name": "Good Will Hunting",
        "rank": 10
    }
]