[
    {
        "name": "The Woman in Cabin 10",
        "rank": 1
    },
    {
        "name": "KPop Demon Hunters",
        "rank": 2
    },
    {
        "name": "My Father, the BTK Killer",
        "rank": 3
    },
    {
        "name": "Steve",
        "rank": 4
    },
    {
        "name": "Priscilla",
        "rank": 5
    },
    {
        "name": "Reunion",
        "rank": 6
    },
    {
        "name": "Caramelo",
        "rank": 7
    },
    {
        "name": "No Good Deed",
        "rank": 8
    },
    {
        "name": "Anyone But You",
        "rank": 9
    },
    {
        "name": "Bad Teacher",
        "rank": 10
    }
]