[
    {
        "name": "Trainwreck: The Real Project X",
        "rank": 1
    },
    {
        "name": "Almost Cops",
        "rank": 2
    },
    {
        "name": "Kraven the Hunter",
        "rank": 3
    },
    {
        "name": "The Old Guard 2",
        "rank": 4
    },
    {
        "name": "Brick",
        "rank": 5
    },
    {
        "name": "KPop Demon Hunters",
        "rank": 6
    },
    {
        "name": "Madea\u2019s Destination Wedding",
        "rank": 7
    },
    {
        "name": "Mr. Monk's Last Case: A Monk Movie",
        "rank": 8
    },
    {
        "name": "The Lesson",
        "rank": 9
    },
    {
        "name": "Trainwreck: Poop Cruise",
        "rank": 10
    }
]