[
    {
        "name": "The Cleaning Lady: Season 1",
        "rank": 1
    },
    {
        "name": "The Cleaning Lady: Season 2",
        "rank": 2
    },
    {
        "name": "Bloodhounds: Season 2",
        "rank": 3
    },
    {
        "name": "Trevor Noah: Joy in The Trenches",
        "rank": 4
    },
    {
        "name": "Salish & Jordan Matter: Season 1",
        "rank": 5
    },
    {
        "name": "The Cleaning Lady: Season 3",
        "rank": 6
    },
    {
        "name": "Million Dollar Secret: Season 2",
        "rank": 7
    },
    {
        "name": "Trust Me: The False Prophet: Season 1",
        "rank": 8
    },
    {
        "name": "Maamla Legal Hai: Season 2",
        "rank": 9
    },
    {
        "name": "Bloodhounds: Season 1",
        "rank": 10
    }
]