[
    {
        "name": "Apex",
        "rank": 1
    },
    {
        "name": "Gladiator II",
        "rank": 2
    },
    {
        "name": "Swapped",
        "rank": 3
    },
    {
        "name": "Love at Last",
        "rank": 4
    },
    {
        "name": "Thrash",
        "rank": 5
    },
    {
        "name": "War Machine",
        "rank": 6
    },
    {
        "name": "180",
        "rank": 7
    },
    {
        "name": "Shooter",
        "rank": 8
    },
    {
        "name": "Roommates",
        "rank": 9
    },
    {
        "name": "Wrong Turn",
        "rank": 10
    }
]