[
    {
        "name": "The Kingdom",
        "rank": 1
    },
    {
        "name": "Materialists",
        "rank": 2
    },
    {
        "name": "The Great Flood",
        "rank": 3
    },
    {
        "name": "Togo",
        "rank": 4
    },
    {
        "name": "And The Breadwinner Is...",
        "rank": 5
    },
    {
        "name": "The Shallows",
        "rank": 6
    },
    {
        "name": "KPop Demon Hunters",
        "rank": 7
    },
    {
        "name": "The Call of the Wild",
        "rank": 8
    },
    {
        "name": "Night Swim",
        "rank": 9
    },
    {
        "name": "Sunshine",
        "rank": 10
    }
]