[
    {
        "name": "Apex",
        "rank": 1
    },
    {
        "name": "Abigail",
        "rank": 2
    },
    {
        "name": "180",
        "rank": 3
    },
    {
        "name": "A Quiet Place: Day One",
        "rank": 4
    },
    {
        "name": "Thrash",
        "rank": 5
    },
    {
        "name": "18th Rose",
        "rank": 6
    },
    {
        "name": "The Fall Guy",
        "rank": 7
    },
    {
        "name": "The Interpreter",
        "rank": 8
    },
    {
        "name": "Shooter",
        "rank": 9
    },
    {
        "name": "Roommates",
        "rank": 10
    }
]