[
    {
        "showId": "81611209",
        "id": "81611209",
        "week": "20241110",
        "rank": 1,
        "weeksInTopTen": 2,
        "country": "sv",
        "category": "films",
        "name": "Let Go",
        "showName": "Let Go",
        "seasonName": "Let Go"
    },
    {
        "showId": "81392060",
        "id": "81392060",
        "week": "20241110",
        "rank": 2,
        "weeksInTopTen": 1,
        "country": "sv",
        "category": "films",
        "name": "Meet Me Next Christmas",
        "showName": "Meet Me Next Christmas",
        "seasonName": "Meet Me Next Christmas"
    },
    {
        "showId": "81073593",
        "id": "81073593",
        "week": "20241110",
        "rank": 3,
        "weeksInTopTen": 4,
        "country": "sv",
        "category": "films",
        "name": "The Angry Birds Movie 2",
        "showName": "The Angry Birds Movie 2",
        "seasonName": "The Angry Birds Movie 2"
    },
    {
        "showId": "81639205",
        "id": "81639205",
        "week": "20241110",
        "rank": 4,
        "weeksInTopTen": 1,
        "country": "sv",
        "category": "films",
        "name": "Scream VI",
        "showName": "Scream VI",
        "seasonName": "Scream VI"
    },
    {
        "showId": "70017961",
        "id": "70017961",
        "week": "20241110",
        "rank": 5,
        "weeksInTopTen": 2,
        "country": "sv",
        "category": "films",
        "name": "Rambo: First Blood Part II",
        "showName": "Rambo: First Blood Part II",
        "seasonName": "Rambo: First Blood Part II"
    },
    {
        "showId": "81504326",
        "id": "81504326",
        "week": "20241110",
        "rank": 6,
        "weeksInTopTen": 2,
        "country": "sv",
        "category": "films",
        "name": "Time Cut",
        "showName": "Time Cut",
        "seasonName": "Time Cut"
    },
    {
        "showId": "70017963",
        "id": "70017963",
        "week": "20241110",
        "rank": 7,
        "weeksInTopTen": 2,
        "country": "sv",
        "category": "films",
        "name": "Rambo: First Blood",
        "showName": "Rambo: First Blood",
        "seasonName": "Rambo: First Blood"
    },
    {
        "showId": "60029370",
        "id": "60029370",
        "week": "20241110",
        "rank": 8,
        "weeksInTopTen": 1,
        "country": "sv",
        "category": "films",
        "name": "Rambo III",
        "showName": "Rambo III",
        "seasonName": "Rambo III"
    },
    {
        "showId": "81322606",
        "id": "81322606",
        "week": "20241110",
        "rank": 9,
        "weeksInTopTen": 1,
        "country": "sv",
        "category": "films",
        "name": "Pedro P\u00c3\u00a1ramo",
        "showName": "Pedro P\u00c3\u00a1ramo",
        "seasonName": "Pedro P\u00c3\u00a1ramo"
    },
    {
        "showId": "81767564",
        "id": "81767564",
        "week": "20241110",
        "rank": 10,
        "weeksInTopTen": 3,
        "country": "sv",
        "category": "films",
        "name": "Don't Move",
        "showName": "Don't Move",
        "seasonName": "Don't Move"
    }
]