[
    {
        "name": "She Said Maybe",
        "rank": 1
    },
    {
        "name": "Man on Fire",
        "rank": 2
    },
    {
        "name": "French Lover",
        "rank": 3
    },
    {
        "name": "Mantis",
        "rank": 4
    },
    {
        "name": "Night Swim",
        "rank": 5
    },
    {
        "name": "Seventh Son",
        "rank": 6
    },
    {
        "name": "The Wrong Paris",
        "rank": 7
    },
    {
        "name": "KPop Demon Hunters",
        "rank": 8
    },
    {
        "name": "Knights of the Zodiac",
        "rank": 9
    },
    {
        "name": "Ruth & Boaz",
        "rank": 10
    }
]