[
    {
        "name": "Chainsaw Man \u2013 The Compilation: Season 1",
        "rank": 1
    },
    {
        "name": "KPop Demon Hunters",
        "rank": 2
    },
    {
        "name": "Honeko Akabane\u2019s Bodyguards",
        "rank": 3
    },
    {
        "name": "Hey Handsome!! The Movie",
        "rank": 4
    },
    {
        "name": "Love Untangled",
        "rank": 5
    },
    {
        "name": "Black Crow 1",
        "rank": 6
    },
    {
        "name": "Black Crow0",
        "rank": 7
    },
    {
        "name": "City Hunter",
        "rank": 8
    },
    {
        "name": "Black Crow3",
        "rank": 9
    },
    {
        "name": "The Thursday Murder Club",
        "rank": 10
    }
]