[
    {
        "name": "A Widow's Game",
        "rank": 26
    },
    {
        "name": "Puss in Boots: The Last Wish",
        "rank": 27
    },
    {
        "name": "Aquaman and the Lost Kingdom",
        "rank": 28
    },
    {
        "name": "The Heart Knows",
        "rank": 29
    },
    {
        "name": "Fear Street: Prom Queen",
        "rank": 30
    },
    {
        "name": "Exterritorial",
        "rank": 31
    },
    {
        "name": "Karol G: Tomorrow was Beautiful",
        "rank": 32
    },
    {
        "name": "Havoc",
        "rank": 33
    },
    {
        "name": "Bad Influence",
        "rank": 34
    },
    {
        "name": "Nonnas",
        "rank": 35
    }
]