[
    {
        "name": "Man on Fire: Season 1",
        "rank": 1
    },
    {
        "name": "Everybody Hates Chris: Season 1",
        "rank": 2
    },
    {
        "name": "Running Point: Season 2",
        "rank": 3
    },
    {
        "name": "Unchosen: Season 1",
        "rank": 4
    },
    {
        "name": "Raw: 2026 - April 27, 2026",
        "rank": 5
    },
    {
        "name": "Should I Marry A Murderer?: Limited Series",
        "rank": 6
    },
    {
        "name": "Bandi: Season 1",
        "rank": 7
    },
    {
        "name": "WWE SmackDown: 2026 - May 1, 2026",
        "rank": 8
    },
    {
        "name": "Million Dollar Secret: Season 2",
        "rank": 9
    },
    {
        "name": "Running Point: Season 1",
        "rank": 10
    }
]