[
    {
        "name": "Roofman",
        "rank": 1
    },
    {
        "name": "Sound of Silence",
        "rank": 2
    },
    {
        "name": "Pavane",
        "rank": 3
    },
    {
        "name": "96 Minutes",
        "rank": 4
    },
    {
        "name": "Firebreak",
        "rank": 5
    },
    {
        "name": "Left-Handed Girl",
        "rank": 6
    },
    {
        "name": "Even If This Love Disappears Tonight",
        "rank": 7
    },
    {
        "name": "KPop Demon Hunters",
        "rank": 8
    },
    {
        "name": "Cosmic Princess Kaguya!",
        "rank": 9
    },
    {
        "name": "Gatao: Big Brothers",
        "rank": 10
    }
]