[
    {
        "name": "Wake Up Dead Man: A Knives Out Mystery",
        "rank": 1
    },
    {
        "name": "Migration",
        "rank": 2
    },
    {
        "name": "Kampung Jabang Mayit: Ritual Maut",
        "rank": 3
    },
    {
        "name": "Troll 2",
        "rank": 4
    },
    {
        "name": "My Secret Santa",
        "rank": 5
    },
    {
        "name": "The Girlfriend",
        "rank": 6
    },
    {
        "name": "Cursed",
        "rank": 7
    },
    {
        "name": "The Call of the Wild",
        "rank": 8
    },
    {
        "name": "STEPHEN",
        "rank": 9
    },
    {
        "name": "Catch Me If You Can",
        "rank": 10
    }
]