[
    {
        "name": "Anaconda",
        "rank": 1
    },
    {
        "name": "Peaky Blinders: The Immortal Man",
        "rank": 2
    },
    {
        "name": "Untold: The Death & Life of Lamar Odom",
        "rank": 3
    },
    {
        "name": "The Truth and Tragedy of Moriah Wilson",
        "rank": 4
    },
    {
        "name": "Smile 2",
        "rank": 5
    },
    {
        "name": "Spider-Man: No Way Home",
        "rank": 6
    },
    {
        "name": "War Machine",
        "rank": 7
    },
    {
        "name": "Trolls World Tour",
        "rank": 8
    },
    {
        "name": "KPop Demon Hunters",
        "rank": 9
    },
    {
        "name": "What Happens in Vegas",
        "rank": 10
    }
]