[
    {
        "name": "Jurassic World Rebirth",
        "rank": 1
    },
    {
        "name": "The Investigation of Lucy Letby",
        "rank": 2
    },
    {
        "name": "Rumble",
        "rank": 3
    },
    {
        "name": "How to Train Your Dragon",
        "rank": 4
    },
    {
        "name": "The Convert",
        "rank": 5
    },
    {
        "name": "The Rip",
        "rank": 6
    },
    {
        "name": "A Quiet Place: Day One",
        "rank": 7
    },
    {
        "name": "Deeper",
        "rank": 8
    },
    {
        "name": "KPop Demon Hunters",
        "rank": 9
    },
    {
        "name": "Joe\u2019s College Road Trip",
        "rank": 10
    }
]