[
    {
        "name": "Black Adam",
        "rank": 1
    },
    {
        "name": "The Elixir",
        "rank": 2
    },
    {
        "name": "KPop Demon Hunters",
        "rank": 3
    },
    {
        "name": "A HOUSE OF DYNAMITE",
        "rank": 4
    },
    {
        "name": "The Perfect Neighbor",
        "rank": 5
    },
    {
        "name": "Despicable Me 4",
        "rank": 6
    },
    {
        "name": "Ordinary Angels",
        "rank": 7
    },
    {
        "name": "With Open Arms",
        "rank": 8
    },
    {
        "name": "The Wrath of Becky",
        "rank": 9
    },
    {
        "name": "The Twits",
        "rank": 10
    }
]