[
    {
        "name": "Swapped",
        "rank": 1
    },
    {
        "name": "My Dearest Assassin",
        "rank": 2
    },
    {
        "name": "Apex",
        "rank": 3
    },
    {
        "name": "Joint Custody",
        "rank": 4
    },
    {
        "name": "Spell",
        "rank": 5
    },
    {
        "name": "Jennifer's Body",
        "rank": 6
    },
    {
        "name": "The Lord of the Rings: The Fellowship of the Ring",
        "rank": 7
    },
    {
        "name": "Miraculous World: Paris, Tales of Shadybug and Claw Noir",
        "rank": 8
    },
    {
        "name": "Mindhunters",
        "rank": 9
    },
    {
        "name": "Remarkably Bright Creatures",
        "rank": 10
    }
]