[
    {
        "name": "Wake Up Dead Man: A Knives Out Mystery",
        "rank": 1
    },
    {
        "name": "Dr. Seuss' The Grinch",
        "rank": 2
    },
    {
        "name": "Murder in Monaco",
        "rank": 3
    },
    {
        "name": "Love Actually",
        "rank": 4
    },
    {
        "name": "Nativity!",
        "rank": 5
    },
    {
        "name": "The Great Flood",
        "rank": 6
    },
    {
        "name": "My Secret Santa",
        "rank": 7
    },
    {
        "name": "How the Grinch Stole Christmas",
        "rank": 8
    },
    {
        "name": "The Christmas Chronicles",
        "rank": 9
    },
    {
        "name": "That Christmas",
        "rank": 10
    }
]