[
    {
        "name": "The Forge",
        "rank": 1
    },
    {
        "name": "Firebreak",
        "rank": 2
    },
    {
        "name": "Accused",
        "rank": 3
    },
    {
        "name": "On aurait d\u00fb aller en Gr\u00e8ce",
        "rank": 4
    },
    {
        "name": "Same Kind of Different as Me",
        "rank": 5
    },
    {
        "name": "Joe\u2019s College Road Trip",
        "rank": 6
    },
    {
        "name": "Sugar and Stars",
        "rank": 7
    },
    {
        "name": "The Addams Family 2",
        "rank": 8
    },
    {
        "name": "The Addams Family",
        "rank": 9
    },
    {
        "name": "State of Fear",
        "rank": 10
    }
]