[
    {
        "name": "Thrash",
        "rank": 1
    },
    {
        "name": "Roommates",
        "rank": 2
    },
    {
        "name": "Husband, Father, Killer: The Alyssa Pladl Story",
        "rank": 3
    },
    {
        "name": "The Requin",
        "rank": 4
    },
    {
        "name": "Nobody Dumps My Daughter",
        "rank": 5
    },
    {
        "name": "Jumanji: Welcome to the Jungle",
        "rank": 6
    },
    {
        "name": "KPop Demon Hunters",
        "rank": 7
    },
    {
        "name": "180",
        "rank": 8
    },
    {
        "name": "Untold: Jail Blazers",
        "rank": 9
    },
    {
        "name": "Halloween Ends",
        "rank": 10
    }
]