[
    {
        "name": "KPop Demon Hunters",
        "rank": 1
    },
    {
        "name": "Happy Gilmore 2",
        "rank": 2
    },
    {
        "name": "My Oxford Year",
        "rank": 3
    },
    {
        "name": "Freelance",
        "rank": 4
    },
    {
        "name": "Journey 2: The Mysterious Island",
        "rank": 5
    },
    {
        "name": "Kandahar",
        "rank": 6
    },
    {
        "name": "Hotel Transylvania 3: Summer Vacation",
        "rank": 7
    },
    {
        "name": "The 5th Wave",
        "rank": 8
    },
    {
        "name": "Megamind",
        "rank": 9
    },
    {
        "name": "Gods of Egypt",
        "rank": 10
    }
]