[
    {
        "name": "KPop Demon Hunters",
        "rank": 1
    },
    {
        "name": "All for Four",
        "rank": 2
    },
    {
        "name": "My Oxford Year",
        "rank": 3
    },
    {
        "name": "Honey",
        "rank": 4
    },
    {
        "name": "Home",
        "rank": 5
    },
    {
        "name": "Night Always Comes",
        "rank": 6
    },
    {
        "name": "Happy Gilmore 2",
        "rank": 7
    },
    {
        "name": "Megamind",
        "rank": 8
    },
    {
        "name": "Elektra",
        "rank": 9
    },
    {
        "name": "Furiosa: A Mad Max Saga",
        "rank": 10
    }
]