[
    {
        "name": "The Rip",
        "rank": 1
    },
    {
        "name": "People We Meet on Vacation",
        "rank": 2
    },
    {
        "name": "It Ends With Us",
        "rank": 3
    },
    {
        "name": "One Last Adventure: The Making of Stranger Things 5",
        "rank": 4
    },
    {
        "name": "Accepted",
        "rank": 5
    },
    {
        "name": "Seks Dla Opornych",
        "rank": 6
    },
    {
        "name": "Gifted Hands: The Ben Carson Story",
        "rank": 7
    },
    {
        "name": "KPop Demon Hunters",
        "rank": 8
    },
    {
        "name": "How to Train Your Dragon: The Hidden World",
        "rank": 9
    },
    {
        "name": "How to Train Your Dragon",
        "rank": 10
    }
]