[
    {
        "name": "HIS & HERS: Limited Series",
        "rank": 1
    },
    {
        "name": "Agatha Christie's Seven Dials: Season 1",
        "rank": 2
    },
    {
        "name": "Run Away: Limited Series",
        "rank": 3
    },
    {
        "name": "To Love, To Lose: Season 1",
        "rank": 4
    },
    {
        "name": "Stranger Things 5",
        "rank": 5
    },
    {
        "name": "The Endless Night: Limited Series",
        "rank": 6
    },
    {
        "name": "Kitty Kotty: Season 2",
        "rank": 7
    },
    {
        "name": "Kitty Kotty: Season 1",
        "rank": 8
    },
    {
        "name": "Alpha Males: Season 4",
        "rank": 9
    },
    {
        "name": "Stranger Things 4",
        "rank": 10
    }
]