[
    {
        "name": "Under a Dark Sun: Season 1",
        "rank": 1
    },
    {
        "name": "Squid Game: Season 3",
        "rank": 2
    },
    {
        "name": "The Sandman: Season 2",
        "rank": 3
    },
    {
        "name": "Aniela: Season 1",
        "rank": 4
    },
    {
        "name": "7 Bears: Limited Series",
        "rank": 5
    },
    {
        "name": "Kres Niewinnosci: Season 1",
        "rank": 6
    },
    {
        "name": "Kitty Kotty: Season 2",
        "rank": 7
    },
    {
        "name": "The Waterfront: Season 1",
        "rank": 8
    },
    {
        "name": "Kitty Kotty: Season 1",
        "rank": 9
    },
    {
        "name": "Olympo: Season 1",
        "rank": 10
    }
]