[
    {
        "name": "Office Romance",
        "rank": 1
    },
    {
        "name": "Colors Of Evil: Black",
        "rank": 2
    },
    {
        "name": "The Marked Woman",
        "rank": 3
    },
    {
        "name": "Caddo Lake",
        "rank": 4
    },
    {
        "name": "Maternal Instinct",
        "rank": 5
    },
    {
        "name": "The Lord of the Rings: The Fellowship of the Ring",
        "rank": 6
    },
    {
        "name": "Poldi",
        "rank": 7
    },
    {
        "name": "The Gunman",
        "rank": 8
    },
    {
        "name": "Goat",
        "rank": 9
    },
    {
        "name": "The Murder of Rachel Nickell",
        "rank": 10
    }
]