[
    {
        "name": "Materialists",
        "rank": 1
    },
    {
        "name": "Abigail",
        "rank": 2
    },
    {
        "name": "The Investigation of Lucy Letby",
        "rank": 3
    },
    {
        "name": "Sweet Home Alabama",
        "rank": 4
    },
    {
        "name": "The Rip",
        "rank": 5
    },
    {
        "name": "KPop Demon Hunters",
        "rank": 6
    },
    {
        "name": "People We Meet on Vacation",
        "rank": 7
    },
    {
        "name": "Ghislaine Maxwell: Filthy Rich",
        "rank": 8
    },
    {
        "name": "Despicable Me 3",
        "rank": 9
    },
    {
        "name": "Frankenstein",
        "rank": 10
    }
]