[
    {
        "name": "Gold Rush Gang",
        "rank": 1
    },
    {
        "name": "Love Untangled",
        "rank": 2
    },
    {
        "name": "Love in the Big City",
        "rank": 3
    },
    {
        "name": "The Thursday Murder Club",
        "rank": 4
    },
    {
        "name": "KPop Demon Hunters",
        "rank": 5
    },
    {
        "name": "The Exorcist: Believer",
        "rank": 6
    },
    {
        "name": "Fall for Me",
        "rank": 7
    },
    {
        "name": "Scouts Guide to the Zombie Apocalypse",
        "rank": 8
    },
    {
        "name": "The Stone",
        "rank": 9
    },
    {
        "name": "Dolittle",
        "rank": 10
    }
]