[
    {
        "name": "Apex",
        "rank": 1
    },
    {
        "name": "Roommates",
        "rank": 2
    },
    {
        "name": "My Favorite Wedding",
        "rank": 3
    },
    {
        "name": "Knocked Up",
        "rank": 4
    },
    {
        "name": "Swapped",
        "rank": 5
    },
    {
        "name": "Speak No Evil",
        "rank": 6
    },
    {
        "name": "Finders Keepers",
        "rank": 7
    },
    {
        "name": "Thrash",
        "rank": 8
    },
    {
        "name": "Buen Camino",
        "rank": 9
    },
    {
        "name": "180",
        "rank": 10
    }
]