[
    {
        "name": "Black Rabbit: Limited Series",
        "rank": 1
    },
    {
        "name": "Beauty and the Bester: Limited Series",
        "rank": 2
    },
    {
        "name": "Wednesday: Season 2",
        "rank": 3
    },
    {
        "name": "Diary of a Ditched Girl: Season 1",
        "rank": 4
    },
    {
        "name": "Adolescence: Limited Series",
        "rank": 5
    },
    {
        "name": "Love Con Revenge: Season 1",
        "rank": 6
    },
    {
        "name": "My Life With the Walter Boys: Season 2",
        "rank": 7
    },
    {
        "name": "Hostage: Limited Series",
        "rank": 8
    },
    {
        "name": "1670: Season 2",
        "rank": 9
    },
    {
        "name": "Beauty in Black: Season 2",
        "rank": 10
    }
]