[
    {
        "name": "I Will Find You: Limited Series",
        "rank": 1
    },
    {
        "name": "Oasis: Season 1",
        "rank": 2
    },
    {
        "name": "Avatar: The Last Airbender: Season 2",
        "rank": 3
    },
    {
        "name": "The Witness: Limited Series",
        "rank": 4
    },
    {
        "name": "Salish & Jordan Matter: Season 2",
        "rank": 5
    },
    {
        "name": "AMERICA'S SWEETHEARTS: Dallas Cowboys Cheerleaders: Season 3",
        "rank": 6
    },
    {
        "name": "Michael Jackson: The Verdict: Season 1",
        "rank": 7
    },
    {
        "name": "Outlast: The Jungle: Season 1",
        "rank": 8
    },
    {
        "name": "The Four Seasons: Season 2",
        "rank": 9
    },
    {
        "name": "Salish & Jordan Matter: Season 1",
        "rank": 10
    }
]