[
    {
        "name": "The Great Flood",
        "rank": 1
    },
    {
        "name": "Wake Up Dead Man: A Knives Out Mystery",
        "rank": 2
    },
    {
        "name": "Migration",
        "rank": 3
    },
    {
        "name": "The Croods: A New Age",
        "rank": 4
    },
    {
        "name": "The 4 Rascals",
        "rank": 5
    },
    {
        "name": "KPop Demon Hunters",
        "rank": 6
    },
    {
        "name": "10DANCE",
        "rank": 7
    },
    {
        "name": "Kumanthong: Untold Story",
        "rank": 8
    },
    {
        "name": "Glass Onion: A Knives Out Mystery",
        "rank": 9
    },
    {
        "name": "Mai",
        "rank": 10
    }
]