[
    {
        "name": "Fall for Me",
        "rank": 1
    },
    {
        "name": "Night Always Comes",
        "rank": 2
    },
    {
        "name": "KPop Demon Hunters",
        "rank": 3
    },
    {
        "name": "My Oxford Year",
        "rank": 4
    },
    {
        "name": "Home",
        "rank": 5
    },
    {
        "name": "Happy Gilmore 2",
        "rank": 6
    },
    {
        "name": "Migration",
        "rank": 7
    },
    {
        "name": "Welcome to Sudden Death",
        "rank": 8
    },
    {
        "name": "Battleship",
        "rank": 9
    },
    {
        "name": "Megamind",
        "rank": 10
    }
]