[
    {
        "name": "The Girlfriend",
        "rank": 1
    },
    {
        "name": "STEPHEN",
        "rank": 2
    },
    {
        "name": "Wake Up Dead Man: A Knives Out Mystery",
        "rank": 3
    },
    {
        "name": "Aaryan (Tamil)",
        "rank": 4
    },
    {
        "name": "Migration",
        "rank": 5
    },
    {
        "name": "Kaantha",
        "rank": 6
    },
    {
        "name": "My Secret Santa",
        "rank": 7
    },
    {
        "name": "Troll 2",
        "rank": 8
    },
    {
        "name": "The Croods: A New Age",
        "rank": 9
    },
    {
        "name": "Sunny Sanskari ki Tulsi Kumari",
        "rank": 10
    }
]