[
    {
        "showId": "80192612",
        "id": "81786168",
        "week": "20241103",
        "rank": 1,
        "weeksInTopTen": 1,
        "country": "lk",
        "category": "tv",
        "name": "Young Sheldon: Season 7",
        "showName": "Young Sheldon",
        "seasonName": "Season 7"
    },
    {
        "showId": "81288983",
        "id": "81486271",
        "week": "20241103",
        "rank": 2,
        "weeksInTopTen": 1,
        "country": "lk",
        "category": "tv",
        "name": "The Diplomat: Season 2",
        "showName": "The Diplomat",
        "seasonName": "Season 2"
    },
    {
        "showId": "81303831",
        "id": "81628779",
        "week": "20241103",
        "rank": 3,
        "weeksInTopTen": 3,
        "country": "lk",
        "category": "tv",
        "name": "The Lincoln Lawyer: Season 3",
        "showName": "The Lincoln Lawyer",
        "seasonName": "Season 3"
    },
    {
        "showId": "81764523",
        "id": "81764524",
        "week": "20241103",
        "rank": 4,
        "weeksInTopTen": 1,
        "country": "lk",
        "category": "tv",
        "name": "Beauty in Black: Season 1",
        "showName": "Beauty in Black",
        "seasonName": "Season 1"
    },
    {
        "showId": "81923548",
        "id": "81923549",
        "week": "20241103",
        "rank": 5,
        "weeksInTopTen": 1,
        "country": "lk",
        "category": "tv",
        "name": "Blippi's Ultimate Bounce House Challenges: Season 1",
        "showName": "Blippi's Ultimate Bounce House Challenges",
        "seasonName": "Season 1"
    },
    {
        "showId": "81681626",
        "id": "81681627",
        "week": "20241103",
        "rank": 6,
        "weeksInTopTen": 2,
        "country": "lk",
        "category": "tv",
        "name": "This Is the Zodiac Speaking: Season 1",
        "showName": "This Is the Zodiac Speaking",
        "seasonName": "Season 1"
    },
    {
        "showId": "81591574",
        "id": "81591575",
        "week": "20241103",
        "rank": 7,
        "weeksInTopTen": 2,
        "country": "lk",
        "category": "tv",
        "name": "Territory: Season 1",
        "showName": "Territory",
        "seasonName": "Season 1"
    },
    {
        "showId": "81641421",
        "id": "81641422",
        "week": "20241103",
        "rank": 8,
        "weeksInTopTen": 1,
        "country": "lk",
        "category": "tv",
        "name": "Don\u00e2\u0080\u0099t Come Home: Limited Series",
        "showName": "Don\u00e2\u0080\u0099t Come Home",
        "seasonName": "Limited Series"
    },
    {
        "showId": "81591296",
        "id": "81591297",
        "week": "20241103",
        "rank": 9,
        "weeksInTopTen": 6,
        "country": "lk",
        "category": "tv",
        "name": "Nobody Wants This: Season 1",
        "showName": "Nobody Wants This",
        "seasonName": "Season 1"
    },
    {
        "showId": "81303831",
        "id": "81303833",
        "week": "20241103",
        "rank": 10,
        "weeksInTopTen": 9,
        "country": "lk",
        "category": "tv",
        "name": "The Lincoln Lawyer: Season 1",
        "showName": "The Lincoln Lawyer",
        "seasonName": "Season 1"
    }
]