[
    {
        "name": "STRAW",
        "rank": 1
    },
    {
        "name": "Titan: The OceanGate Submersible Disaster",
        "rank": 2
    },
    {
        "name": "Trainwreck: The Astroworld Tragedy",
        "rank": 3
    },
    {
        "name": "Wonka",
        "rank": 4
    },
    {
        "name": "The Equalizer 3",
        "rank": 5
    },
    {
        "name": "K.O.",
        "rank": 6
    },
    {
        "name": "North of Normal",
        "rank": 7
    },
    {
        "name": "Radio",
        "rank": 8
    },
    {
        "name": "The Super Mario Bros. Movie",
        "rank": 9
    },
    {
        "name": "Happy Gilmore",
        "rank": 10
    }
]