[
    {
        "name": "The Woman in Cabin 10",
        "rank": 1
    },
    {
        "name": "KPop Demon Hunters",
        "rank": 2
    },
    {
        "name": "Godzilla x Kong: The New Empire",
        "rank": 3
    },
    {
        "name": "My Father, the BTK Killer",
        "rank": 4
    },
    {
        "name": "Caramelo",
        "rank": 5
    },
    {
        "name": "Reunion",
        "rank": 6
    },
    {
        "name": "Wonder Park",
        "rank": 7
    },
    {
        "name": "Anyone But You",
        "rank": 8
    },
    {
        "name": "Fast & Furious Presents: Hobbs & Shaw",
        "rank": 9
    },
    {
        "name": "The Missing",
        "rank": 10
    }
]