[
    {
        "name": "Ladies First",
        "rank": 1
    },
    {
        "name": "Kara",
        "rank": 2
    },
    {
        "name": "Speak No Evil",
        "rank": 3
    },
    {
        "name": "One More Shot",
        "rank": 4
    },
    {
        "name": "Zack Snyder's Justice League",
        "rank": 5
    },
    {
        "name": "The Lotto Winner",
        "rank": 6
    },
    {
        "name": "Dhurandhar The Revenge (Raw & Undekha)",
        "rank": 7
    },
    {
        "name": "Swapped",
        "rank": 8
    },
    {
        "name": "Apex",
        "rank": 9
    },
    {
        "name": "Alzarfah: Escape from Hanhounia Hell",
        "rank": 10
    }
]