[
    {
        "name": "Apex",
        "rank": 1
    },
    {
        "name": "180",
        "rank": 2
    },
    {
        "name": "Roommates",
        "rank": 3
    },
    {
        "name": "The Killer",
        "rank": 4
    },
    {
        "name": "Despicable Me 4",
        "rank": 5
    },
    {
        "name": "Materialists",
        "rank": 6
    },
    {
        "name": "The Interpreter",
        "rank": 7
    },
    {
        "name": "Thrash",
        "rank": 8
    },
    {
        "name": "Shooter",
        "rank": 9
    },
    {
        "name": "Uncommon Valor",
        "rank": 10
    }
]