[
    {
        "name": "Family Business",
        "rank": 1
    },
    {
        "name": "No Time to Die",
        "rank": 2
    },
    {
        "name": "Voicemails for Isabelle",
        "rank": 3
    },
    {
        "name": "Bhooth Bangla",
        "rank": 4
    },
    {
        "name": "Maternal Instinct",
        "rank": 5
    },
    {
        "name": "The Marked Woman",
        "rank": 6
    },
    {
        "name": "Alzarfah: Escape from Hanhounia Hell",
        "rank": 7
    },
    {
        "name": "Office Romance",
        "rank": 8
    },
    {
        "name": "Skyfall",
        "rank": 9
    },
    {
        "name": "Husbands in Action",
        "rank": 10
    }
]